api_client_v2/__init__.py
api_client_v2/api_client.py
api_client_v2/api_response.py
api_client_v2/configuration.py
api_client_v2/exceptions.py
api_client_v2/py.typed
api_client_v2/rest.py
api_client_v2/api/__init__.py
api_client_v2/api/api_key_api.py
api_client_v2/api/api_key_model_api.py
api_client_v2/api/api_key_model_verify_api.py
api_client_v2/api/api_key_model_versioning_api.py
api_client_v2/api/api_key_repository_api.py
api_client_v2/models/__init__.py
api_client_v2/models/models_api_key_histories.py
api_client_v2/models/models_api_key_info.py
api_client_v2/models/models_api_key_package.py
api_client_v2/models/models_commit.py
api_client_v2/models/models_commit_meta.py
api_client_v2/models/models_commit_stats.py
api_client_v2/models/models_commit_user.py
api_client_v2/models/models_follow.py
api_client_v2/models/models_member.py
api_client_v2/models/models_model_versioning.py
api_client_v2/models/models_model_versioning_group_lite.py
api_client_v2/models/models_offer.py
api_client_v2/models/models_platform_task.py
api_client_v2/models/models_queue_task.py
api_client_v2/models/models_repo_commit.py
api_client_v2/models/models_user.py
api_client_v2/models/models_wallet.py
api_client_v2/models/models_wallet_with_address.py
api_client_v2/models/request_calculate_cost_to_verify_ai_model_request.py
api_client_v2/models/request_check_valid_to_verify_ai_model_request.py
api_client_v2/models/request_distribute_task_request.py
api_client_v2/models/request_get_api_key_statistics_by_model_id_request.py
api_client_v2/models/request_verify_ai_model_request.py
api_client_v2/models/response_api_key_history_list_data.py
api_client_v2/models/response_api_key_history_list_response.py
api_client_v2/models/response_api_key_info_response.py
api_client_v2/models/response_check_model_is_serving_data.py
api_client_v2/models/response_check_model_is_serving_response.py
api_client_v2/models/response_check_valid_to_verify_ai_model_data.py
apiclientv2-1.0.4.dist-info/METADATA
apiclientv2-1.0.4.dist-info/WHEEL
apiclientv2-1.0.4.dist-info/top_level.txt
apiclientv2-1.0.4.dist-info/RECORD
