Metadata-Version: 2.4
Name: ApiClientV2
Version: 1.0.4
Summary: AIOZ-AI-PLATFORM API
Home-page: 
Author: API Support
Author-email: support@swagger.io
License: Apache 2.0
Keywords: OpenAPI,OpenAPI-Generator,AIOZ-AI-PLATFORM API
Requires-Dist: urllib3<3.0.0,>=1.25.3
Requires-Dist: python-dateutil>=2.8.2
Requires-Dist: pydantic>=2
Requires-Dist: typing-extensions>=4.7.1
Dynamic: author
Dynamic: author-email
Dynamic: description
Dynamic: description-content-type
Dynamic: keywords
Dynamic: license
Dynamic: requires-dist
Dynamic: summary
